tests/__init__.py
tests/test_availability_api.py
tests/test_cdx_api.py
tests/test_cdx_snapshot.py
tests/test_cdx_utils.py
tests/test_cli.py
tests/test_save_api.py
tests/test_utils.py
tests/test_wrapper.py
waybackpy/__init__.py
waybackpy/availability_api.py
waybackpy/cdx_api.py
waybackpy/cdx_snapshot.py
waybackpy/cdx_utils.py
waybackpy/cli.py
waybackpy/exceptions.py
waybackpy/save_api.py
waybackpy/utils.py
waybackpy/wrapper.py
waybackpy-3.0.5.dist-info/LICENSE
waybackpy-3.0.5.dist-info/METADATA
waybackpy-3.0.5.dist-info/WHEEL
waybackpy-3.0.5.dist-info/entry_points.txt
waybackpy-3.0.5.dist-info/top_level.txt
waybackpy-3.0.5.dist-info/RECORD
