Metadata-Version: 2.1
Name: waybackpy
Version: 3.0.5
Summary: Python package that interfaces with the Internet Archive's Wayback Machine APIs. Archive pages and retrieve archived pages easily.
Home-page: https://akamhy.github.io/waybackpy/
Author: Akash Mahanty
Author-email: akamhy@yahoo.com
License: MIT
Download-URL: https://github.com/akamhy/waybackpy/releases
Project-URL: Documentation, https://github.com/akamhy/waybackpy/wiki
Project-URL: Source, https://github.com/akamhy/waybackpy
Project-URL: Tracker, https://github.com/akamhy/waybackpy/issues
Keywords: Archive Website,Wayback Machine,Internet Archive,Wayback Machine CLI,Wayback Machine Python,Internet Archiving,Availability API,CDX API,savepagenow
Platform: UNKNOWN
Classifier: Development Status :: 5 - Production/Stable
Classifier: Intended Audience :: Developers
Classifier: Intended Audience :: End Users/Desktop
Classifier: Natural Language :: English
Classifier: Typing :: Typed
Classifier: License :: OSI Approved :: MIT License
Classifier: Programming Language :: Python
Classifier: Programming Language :: Python :: 3
Classifier: Programming Language :: Python :: 3.6
Classifier: Programming Language :: Python :: 3.7
Classifier: Programming Language :: Python :: 3.8
Classifier: Programming Language :: Python :: 3.9
Classifier: Programming Language :: Python :: 3.10
Classifier: Programming Language :: Python :: Implementation :: CPython
Requires-Python: >=3.6
License-File: LICENSE
Requires-Dist: click
Requires-Dist: requests
Requires-Dist: urllib3
Provides-Extra: dev
Requires-Dist: black ; extra == 'dev'
Requires-Dist: codecov ; extra == 'dev'
Requires-Dist: flake8 ; extra == 'dev'
Requires-Dist: mypy ; extra == 'dev'
Requires-Dist: pytest ; extra == 'dev'
Requires-Dist: pytest-cov ; extra == 'dev'
Requires-Dist: setuptools (>=46.4.0) ; extra == 'dev'
Requires-Dist: types-requests ; extra == 'dev'
